{"_id":"pGJmHaRBSENObTfD","name":"重庆文理学院（红河校区）","status":"OPENING","opening-time":"9:00--22:00","address":"重庆市永川区立秋路","_createTime":1684060528277,"_updateTime":1684157378408,"opening_time":"9:30~21:00","location":{"coordinates":[105.939318,29.348259],"type":"Point"},"phone":"17623770623"}
{"_id":"hoiLhqqvT9GyuQZW","name":"永川华贸国际中心店","status":"CLOSED","opening-time":"9:00--22:00","address":"重庆市永川区常州大道华贸国际中心L1C17","_createTime":1684060789877,"_updateTime":1684063081545,"opening_time":"9:00~22:00","location":{"type":"Point","coordinates":[105.93,29.36]}}
{"_id":"jiip6tC5Ku6sx5Lo","name":"重庆龙湖时代天街店","status":"OPENING","opening-time":"9:00--22:00","address":"重庆市渝中区龙湖时代天街1号龙湖时代天街2楼A2002","_createTime":1684060967588,"_updateTime":1684063096850,"opening_time":"9:30~22:00","location":{"coordinates":[106.51,29.54],"type":"Point"}}
